MANIFEST.in
README.md
requirements-test.txt
setup.py
criticalpath/__init__.py
criticalpath/criticalpath.py
criticalpath/tests.py
criticalpath.egg-info/PKG-INFO
criticalpath.egg-info/SOURCES.txt
criticalpath.egg-info/dependency_links.txt
criticalpath.egg-info/not-zip-safe
criticalpath.egg-info/top_level.txt
criticalpath/fixtures/deps_big.dsv
criticalpath/fixtures/deps_small.dsv
criticalpath/fixtures/timings.dsv